xhp_flow/__init__.py
xhp_flow/nn/__init__.py
xhp_flow/nn/core.py
xhp_flow/utils/__init__.py
xhp_flow/utils/util.py
xhpflow_1.0-0.0.1.dist-info/LICENSE
xhpflow_1.0-0.0.1.dist-info/METADATA
xhpflow_1.0-0.0.1.dist-info/WHEEL
xhpflow_1.0-0.0.1.dist-info/top_level.txt
xhpflow_1.0-0.0.1.dist-info/RECORD
