Metadata-Version: 2.1
Name: xhpflow-1.0
Version: 0.0.1
Summary: This is a mini but function competed neural networks framwork
Home-page: UNKNOWN
Author: xiaohaipeng
Author-email: 307153814@qq.com
License: UNKNOWN
Platform: UNKNOWN
Classifier: Programming Language :: Python :: 3
Classifier: License :: OSI Approved :: MIT License
Classifier: Operating System :: OS Independent
Requires-Python: >=3.5
